{"IntentId":"b8e4812cd2eb2a04","TradingDate":"2026-05-12","Stream":"ES2","Instrument":"MES","EntrySubmitted":true,"EntrySubmittedAt":"2026-05-12T16:00:01.6256899+00:00","EntrySubmittedAtUtc":"2026-05-12T16:00:01.6256899+00:00","EntrySubmittedObservedAtUtc":"2026-05-12T19:50:01.2696008+00:00","EntryFilled":true,"EntryFilledAt":"2026-05-12T19:32:52.1655654+00:00","EntryFilledObservedAtUtc":"2026-05-12T19:32:52.1655654+00:00","IsReconstructedSubmission":true,"BrokerOrderId":"fef1466e8ec94bdc8a38a6b707408d91","EntryOrderType":"ENTRY_STOP","FillPrice":7421,"FillQuantity":2,"Rejected":false,"RejectedAt":null,"RejectionReason":null,"ProtectiveRejectedAt":null,"ProtectiveRejectionReason":null,"ProtectiveRejectionOrderType":null,"ProtectiveRejectedPrice":null,"ProtectiveRejectedQuantity":null,"BEModified":true,"BEModifiedAt":"2026-05-12T19:50:01.2696008+00:00","BEStopPrice":7420.75,"PreviousStopPrice":7391,"BETriggerPrice":7427.500,"Direction":"Long","EntryPrice":7421.00,"StopPrice":7391.00,"TargetPrice":7431.00,"OcoGroup":"QTSW2:OCO_ENTRY:2026-05-12:ES2:11:00:0d3725b23a7c4029b58cf638a1c40ccd","RejectionOrderType":null,"RejectedPrice":null,"RejectedQuantity":null,"ExpectedEntryPrice":null,"ActualFillPrice":7421,"SlippagePoints":null,"SlippageDollars":null,"Commission":null,"Fees":null,"TotalCost":null,"ContractMultiplier":5,"EntryFilledQuantityTotal":2,"EntryAvgFillPrice":7421,"EntryFillNotional":14842,"EntryFilledAtUtc":"2026-05-12T19:32:52.1655654+00:00","ExitFilledQuantityTotal":2,"ExitAvgFillPrice":7431,"ExitFillNotional":14862,"ExitOrderType":"TARGET","ExitFilledAtUtc":"2026-05-12T19:53:07.3482871+00:00","ExitFilledObservedAtUtc":"2026-05-12T19:53:07.3482871+00:00","IntentType":null,"RecoverySource":null,"RecoveryTimestampUtc":null,"RecoveredQuantity":null,"RecoveredPrice":null,"IsRecovered":false,"OriginalIntentId":null,"TradeCompleted":true,"RealizedPnLGross":100,"RealizedPnLNet":100,"RealizedPnLPoints":10,"CompletionReason":"TARGET","CompletedAtUtc":"2026-05-12T19:53:07.3482871+00:00"}