{"ExitOrderType":"ENTRY_CANCELLED_UNFILLED","ExitFilledAtUtc":null,"ExitFilledObservedAtUtc":null,"IntentType":null,"RecoverySource":null,"IntentId":"0548bbd5a0863ec7","RecoveryTimestampUtc":null,"TradingDate":"2026-05-12","RecoveredQuantity":null,"Stream":"ES1","Instrument":"MES","RecoveredPrice":null,"EntrySubmitted":true,"IsRecovered":false,"EntrySubmittedAt":"2026-05-12T13:01:01.9572765+00:00","OriginalIntentId":null,"EntrySubmittedAtUtc":"2026-05-12T13:01:01.9572765+00:00","TradeCompleted":true,"EntrySubmittedObservedAtUtc":"2026-05-12T13:01:01.2894989+00:00","RealizedPnLGross":null,"EntryFilled":false,"RealizedPnLNet":null,"EntryFilledAt":null,"RealizedPnLPoints":null,"EntryFilledObservedAtUtc":null,"CompletionReason":"ENTRY_CANCELLED_UNFILLED","IsReconstructedSubmission":false,"CompletedAtUtc":"2026-05-12T13:57:10.3999899+00:00","BrokerOrderId":"f0fff2705e634624a9d9640d03d89683","EntryOrderType":"ENTRY_STOP","FillPrice":null,"FillQuantity":null,"Rejected":false,"RejectedAt":null,"RejectionReason":null,"BEModified":false,"BEModifiedAt":null,"BEStopPrice":null,"PreviousStopPrice":null,"BETriggerPrice":7427.500,"Direction":"Long","EntryPrice":7421.00,"StopPrice":7396.25,"TargetPrice":7431.00,"OcoGroup":"QTSW2:OCO_ENTRY:2026-05-12:ES1:08:00:b64b15dbac5140f39ecc066e47a8b720","RejectionOrderType":null,"RejectedPrice":null,"RejectedQuantity":null,"ExpectedEntryPrice":null,"ActualFillPrice":null,"SlippagePoints":null,"SlippageDollars":null,"Commission":null,"Fees":null,"TotalCost":null,"ContractMultiplier":null,"EntryFilledQuantityTotal":0,"EntryAvgFillPrice":null,"EntryFillNotional":null,"EntryFilledAtUtc":null,"ExitFilledQuantityTotal":0,"ExitAvgFillPrice":null,"ExitFillNotional":null,"ProtectiveRejectedAt":null,"ProtectiveRejectionReason":null,"ProtectiveRejectionOrderType":null,"ProtectiveRejectedPrice":null,"ProtectiveRejectedQuantity":null}