{"TradingDate":"2026-04-27","Stream":"NG2","Committed":false,"CommitReason":null,"TerminalState":null,"LastState":"RANGE_LOCKED","LastUpdateUtc":"2026-04-27T20:55:00.0000000+00:00","TimetableHashAtCommit":null,"StopBracketsSubmittedAtLock":true,"PostLockLongBreakoutTouched":false,"PostLockShortBreakoutTouched":false,"EntryDetected":false,"SlotInstanceKey":"NG2_11:00_2026-04-27","SlotStatus":0,"ExecutionInterruptedByClose":false,"ForcedFlattenTimestamp":"\/Date(1777323300000)\/","OriginalIntentId":"175727cc0165211f","ReentryIntentId":"5720772f3863a833","ReentrySubmitPending":false,"ReentrySubmitPendingAtUtc":null,"ReentrySubmitLastFailureUtc":null,"ReentrySubmitFailureCount":0,"LastReentrySubmitError":null,"ReentrySubmitted":true,"ReentryFilled":true,"ProtectionSubmitted":true,"ProtectionAccepted":true,"NextSlotTimeUtc":"\/Date(1777392000000)\/","PriorJournalKey":null,"RecoveryAction":null,"RecoveryActionReason":null,"RecoveryActionIssuedUtc":null}