{"IntentId":"b0764167f96d958c","TradingDate":"2026-04-28","TotalCost":null,"Stream":"GC1","Instrument":"MGC","ContractMultiplier":null,"EntrySubmitted":true,"EntryFilledQuantityTotal":0,"EntrySubmittedAt":"2026-05-09T20:46:30.1251938+00:00","EntrySubmittedAtUtc":"2026-05-09T20:46:30.1251938+00:00","EntryAvgFillPrice":null,"EntrySubmittedObservedAtUtc":"2026-04-28T12:30:00.0000000+00:00","EntryFillNotional":null,"EntryFilled":false,"EntryFilledAt":null,"EntryFilledAtUtc":null,"EntryFilledObservedAtUtc":null,"ExitFilledQuantityTotal":0,"IsReconstructedSubmission":false,"ExitAvgFillPrice":null,"BrokerOrderId":"d64233eea8b4456fbecd83e5443b961b","ExitFillNotional":null,"EntryOrderType":"ENTRY_STOP","ExitOrderType":"ENTRY_CANCELLED_UNFILLED","FillPrice":null,"ExitFilledAtUtc":null,"FillQuantity":null,"ExitFilledObservedAtUtc":null,"Rejected":false,"IntentType":null,"RejectedAt":null,"RecoverySource":null,"RejectionReason":null,"RecoveryTimestampUtc":null,"ProtectiveRejectedAt":null,"RecoveredQuantity":null,"ProtectiveRejectionReason":null,"RecoveredPrice":null,"ProtectiveRejectionOrderType":null,"IsRecovered":false,"ProtectiveRejectedPrice":null,"OriginalIntentId":null,"ProtectiveRejectedQuantity":null,"TradeCompleted":true,"BEModified":false,"RealizedPnLGross":null,"BEModifiedAt":null,"RealizedPnLNet":null,"BEStopPrice":null,"RealizedPnLPoints":null,"PreviousStopPrice":null,"CompletionReason":"ENTRY_CANCELLED_UNFILLED","BETriggerPrice":4564.150,"CompletedAtUtc":"2026-05-09T21:03:54.7583179+00:00","Direction":"Short","EntryPrice":4567.4,"StopPrice":4582.4,"TargetPrice":4562.4,"OcoGroup":"QTSW2:OCO_ENTRY:2026-04-28:GC1:07:30:c994f209dd584dd580b962367f98e734","RejectionOrderType":null,"RejectedPrice":null,"RejectedQuantity":null,"ExpectedEntryPrice":null,"ActualFillPrice":null,"SlippagePoints":null,"SlippageDollars":null,"Commission":null,"Fees":null}