{"IntentId":"UNTR38e0d66b1fcd13ed","TradingDate":"RECOVERY","Stream":"UNTRACKED_RECOVERY","Instrument":"MGC","EntrySubmitted":true,"EntrySubmittedAt":"2026-04-12T23:49:50.6058528\u002B00:00","EntrySubmittedAtUtc":"2026-04-12T23:49:50.6058528\u002B00:00","EntrySubmittedObservedAtUtc":"2026-04-12T23:49:50.6966088\u002B00:00","EntryFilled":true,"EntryFilledAt":"2026-04-12T23:49:50.6058528\u002B00:00","EntryFilledObservedAtUtc":"2026-04-12T23:49:50.6966088\u002B00:00","IsReconstructedSubmission":true,"BrokerOrderId":"586d66effd18421b9c0033338ee01237","EntryOrderType":"UNTRACKED_FILL_RECOVERY","FillPrice":4758.3,"FillQuantity":1,"Rejected":false,"RejectedAt":null,"RejectionReason":null,"BEModified":false,"BEModifiedAt":null,"BEStopPrice":null,"PreviousStopPrice":null,"BETriggerPrice":null,"Direction":"Long","EntryPrice":null,"StopPrice":null,"TargetPrice":null,"OcoGroup":null,"RejectionOrderType":null,"RejectedPrice":null,"RejectedQuantity":null,"ExpectedEntryPrice":null,"ActualFillPrice":4758.3,"SlippagePoints":null,"SlippageDollars":null,"Commission":null,"Fees":null,"TotalCost":null,"ContractMultiplier":null,"EntryFilledQuantityTotal":1,"EntryAvgFillPrice":null,"EntryFillNotional":null,"EntryFilledAtUtc":"2026-04-12T23:49:50.6058528\u002B00:00","ExitFilledQuantityTotal":1,"ExitAvgFillPrice":null,"ExitFillNotional":null,"ExitOrderType":"UNTRACKED_FILL_RECOVERY_FLAT","ExitFilledAtUtc":"2026-04-12T23:49:50.5957886\u002B00:00","ExitFilledObservedAtUtc":null,"IntentType":null,"RecoverySource":null,"RecoveryTimestampUtc":null,"RecoveredQuantity":null,"RecoveredPrice":null,"IsRecovered":false,"OriginalIntentId":null,"TradeCompleted":true,"RealizedPnLGross":null,"RealizedPnLNet":null,"RealizedPnLPoints":null,"CompletionReason":"UNTRACKED_FILL_RECOVERY_FLAT","CompletedAtUtc":"2026-04-12T23:49:50.7556445\u002B00:00"}