{"TradingDate":"2026-05-07","Stream":"NG2","Committed":false,"CommitReason":null,"TerminalState":null,"LastState":"RANGE_LOCKED","LastUpdateUtc":"2026-05-07T16:01:03.6400863+00:00","TimetableHashAtCommit":null,"StopBracketsSubmittedAtLock":true,"PostLockLongBreakoutTouched":false,"PostLockShortBreakoutTouched":false,"EntryDetected":false,"SlotInstanceKey":"NG2_11:00_2026-05-07","SlotStatus":0,"ExecutionInterruptedByClose":false,"ForcedFlattenTimestamp":"\/Date(1778187413771)\/","OriginalIntentId":"b5a9aa5158bc84df","ReentryIntentId":"53b4c26ef93068e1","ReentrySubmitPending":false,"ReentrySubmitPendingAtUtc":null,"ReentrySubmitLastFailureUtc":null,"ReentrySubmitFailureCount":0,"LastReentrySubmitError":null,"ReentrySubmitted":true,"ReentryFilled":true,"ProtectionSubmitted":true,"ProtectionAccepted":true,"NextSlotTimeUtc":"\/Date(1778256000000)\/","PriorJournalKey":null,"RecoveryAction":null,"RecoveryActionReason":null,"RecoveryActionIssuedUtc":null}