{"IntentId":"bb425b83faa8dfa0","TradingDate":"2026-04-27","Stream":"NQ2","Instrument":"MNQ","EntrySubmitted":true,"EntrySubmittedAt":"2026-05-05T20:36:17.4282816+00:00","EntrySubmittedAtUtc":"2026-05-05T20:36:17.4282816+00:00","EntrySubmittedObservedAtUtc":"2026-05-05T20:42:26.1304335+00:00","EntryFilled":true,"EntryFilledAt":"2026-05-05T20:42:26.1304335+00:00","EntryFilledObservedAtUtc":"2026-05-05T20:42:26.1304335+00:00","IsReconstructedSubmission":false,"BrokerOrderId":"3f2b3ff5bc3248a2b349b212ddef77d3","EntryOrderType":"ENTRY_STOP","FillPrice":27433.75,"FillQuantity":1,"Rejected":false,"RejectedAt":null,"RejectionReason":null,"ProtectiveRejectedAt":null,"ProtectiveRejectionReason":null,"ProtectiveRejectionOrderType":null,"ProtectiveRejectedPrice":null,"ProtectiveRejectedQuantity":null,"BEModified":false,"BEModifiedAt":null,"BEStopPrice":null,"PreviousStopPrice":null,"BETriggerPrice":27466.250,"Direction":"Long","EntryPrice":27433.75,"StopPrice":27298.25,"TargetPrice":27483.75,"OcoGroup":"QTSW2:OCO_ENTRY:2026-04-27:NQ2:09:30:b9ae63adfdbd4d9a81a14235f0639827","RejectionOrderType":null,"RejectedPrice":null,"RejectedQuantity":null,"ExpectedEntryPrice":null,"ActualFillPrice":27433.75,"SlippagePoints":null,"SlippageDollars":null,"Commission":null,"Fees":null,"TotalCost":null,"ContractMultiplier":2,"EntryFilledQuantityTotal":1,"EntryAvgFillPrice":27433.75,"EntryFillNotional":27433.75,"EntryFilledAtUtc":"2026-05-05T20:42:26.1304335+00:00","ExitFilledQuantityTotal":1,"ExitAvgFillPrice":27423.5,"ExitFillNotional":27423.5,"ExitOrderType":"FLATTEN","ExitFilledAtUtc":"2026-05-05T20:49:14.1223423+00:00","ExitFilledObservedAtUtc":"2026-05-05T20:49:14.1223423+00:00","IntentType":null,"RecoverySource":null,"RecoveryTimestampUtc":null,"RecoveredQuantity":null,"RecoveredPrice":null,"IsRecovered":false,"OriginalIntentId":null,"TradeCompleted":true,"RealizedPnLGross":-20.50,"RealizedPnLNet":-20.50,"RealizedPnLPoints":-10.25,"CompletionReason":"FLATTEN","CompletedAtUtc":"2026-05-05T20:49:14.1223423+00:00"}