{"IntentId":"175727cc0165211f","TradingDate":"2026-04-27","Stream":"NG2","Instrument":"MNG","EntrySubmitted":true,"EntrySubmittedAt":"2026-05-05T22:51:06.3774092+00:00","EntrySubmittedAtUtc":"2026-05-05T22:51:06.3774092+00:00","EntrySubmittedObservedAtUtc":"2026-05-05T22:53:57.1159041+00:00","EntryFilled":true,"EntryFilledAt":"2026-05-05T22:53:57.1159041+00:00","EntryFilledObservedAtUtc":"2026-05-05T22:53:57.1159041+00:00","IsReconstructedSubmission":false,"BrokerOrderId":"a0ed018d6cc54fe680caee016abb5f88","EntryOrderType":"ENTRY_STOP","FillPrice":2.761,"FillQuantity":2,"Rejected":false,"RejectedAt":null,"RejectionReason":null,"ProtectiveRejectedAt":null,"ProtectiveRejectionReason":null,"ProtectiveRejectionOrderType":null,"ProtectiveRejectedPrice":null,"ProtectiveRejectedQuantity":null,"BEModified":false,"BEModifiedAt":null,"BEStopPrice":null,"PreviousStopPrice":null,"BETriggerPrice":2.7285,"Direction":"Short","EntryPrice":2.761,"StopPrice":2.808,"TargetPrice":2.711,"OcoGroup":"QTSW2:OCO_ENTRY:2026-04-27:NG2:11:00:c3940385d36847e2adcec4635f33c42b","RejectionOrderType":null,"RejectedPrice":null,"RejectedQuantity":null,"ExpectedEntryPrice":null,"ActualFillPrice":2.761,"SlippagePoints":null,"SlippageDollars":null,"Commission":null,"Fees":null,"TotalCost":null,"ContractMultiplier":1000,"EntryFilledQuantityTotal":2,"EntryAvgFillPrice":2.761,"EntryFillNotional":5.522,"EntryFilledAtUtc":"2026-05-05T22:53:57.1159041+00:00","ExitFilledQuantityTotal":2,"ExitAvgFillPrice":2.711,"ExitFillNotional":5.422,"ExitOrderType":"TARGET","ExitFilledAtUtc":"2026-05-05T23:23:27.9024484+00:00","ExitFilledObservedAtUtc":"2026-05-05T23:23:27.9024484+00:00","IntentType":null,"RecoverySource":null,"RecoveryTimestampUtc":null,"RecoveredQuantity":null,"RecoveredPrice":null,"IsRecovered":false,"OriginalIntentId":null,"TradeCompleted":true,"RealizedPnLGross":100.000,"RealizedPnLNet":100.000,"RealizedPnLPoints":0.050,"CompletionReason":"TARGET","CompletedAtUtc":"2026-05-05T23:23:27.9024484+00:00"}